<?xml version="1.0" encoding="UTF-8" standalone="yes"?>
<agentsStatistics>
    <statistics>
        <agentname>TitForTatAgentTB</agentname>
        <totalUndiscountedUtility>6.540984522118316</totalUndiscountedUtility>
        <totalDiscountedUtility>5.205259975143775</totalDiscountedUtility>
        <numberOfSessions>8</numberOfSessions>
        <totalNashDist>1.2036686412284707</totalNashDist>
        <totalWelfare>10.912489903314855</totalWelfare>
        <totalParetoDistance>0.42112599193072775</totalParetoDistance>
        <meanDiscounted>0.6506574968929719</meanDiscounted>
        <meanNashDistance>0.15045858015355884</meanNashDistance>
        <meanParetoDistance>0.05264074899134097</meanParetoDistance>
        <meanUndiscounted>0.8176230652647895</meanUndiscounted>
        <meanWelfare>1.3640612379143568</meanWelfare>
    </statistics>
    <statistics>
        <agentname>agents.TimeDependentAgentConceder</agentname>
        <totalUndiscountedUtility>6.963768608416982</totalUndiscountedUtility>
        <totalDiscountedUtility>6.519244669372255</totalDiscountedUtility>
        <numberOfSessions>8</numberOfSessions>
        <totalNashDist>1.4178222510754908</totalNashDist>
        <totalWelfare>12.965836513477017</totalWelfare>
        <totalParetoDistance>0.1842160377293267</totalParetoDistance>
        <meanDiscounted>0.8149055836715319</meanDiscounted>
        <meanNashDistance>0.17722778138443634</meanNashDistance>
        <meanParetoDistance>0.02302700471616584</meanParetoDistance>
        <meanUndiscounted>0.8704710760521227</meanUndiscounted>
        <meanWelfare>1.620729564184627</meanWelfare>
    </statistics>
    <statistics>
        <agentname>agents.TimeDependentAgentBoulware</agentname>
        <totalUndiscountedUtility>7.6891814978198205</totalUndiscountedUtility>
        <totalDiscountedUtility>6.058896931754899</totalDiscountedUtility>
        <numberOfSessions>8</numberOfSessions>
        <totalNashDist>0.8382565391657283</totalNashDist>
        <totalWelfare>11.068259021507261</totalWelfare>
        <totalParetoDistance>0.0</totalParetoDistance>
        <meanDiscounted>0.7573621164693624</meanDiscounted>
        <meanNashDistance>0.10478206739571604</meanNashDistance>
        <meanParetoDistance>0.0</meanParetoDistance>
        <meanUndiscounted>0.9611476872274776</meanUndiscounted>
        <meanWelfare>1.3835323776884076</meanWelfare>
    </statistics>
    <statistics>
        <agentname>negotiator.parties.RandomParty</agentname>
        <totalUndiscountedUtility>6.154690848261438</totalUndiscountedUtility>
        <totalDiscountedUtility>4.8568848268738805</totalDiscountedUtility>
        <numberOfSessions>8</numberOfSessions>
        <totalNashDist>1.2708875704839697</totalNashDist>
        <totalWelfare>10.333987367990487</totalWelfare>
        <totalParetoDistance>0.48496169999542627</totalParetoDistance>
        <meanDiscounted>0.6071106033592351</meanDiscounted>
        <meanNashDistance>0.15886094631049621</meanNashDistance>
        <meanParetoDistance>0.06062021249942828</meanParetoDistance>
        <meanUndiscounted>0.7693363560326798</meanUndiscounted>
        <meanWelfare>1.2917484209988108</meanWelfare>
    </statistics>
</agentsStatistics>
